Metadata-Version: 2.1
Name: MVEn
Version: 1.1.5
Summary: demo
Author: megnet
Author-email: 1060388271@qq.com
License: apache 3.0
Requires: importlib
Requires: matplotlib
Requires: math
Requires: re
Requires: sys
Requires: typing
Requires: numpy
Requires: torch
Requires: PIL
Requires: os
Requires: datasets
Requires: cv2
Requires: random
Requires: computecampair
Requires: compute_camspairCC
Requires: computesfm
Requires: typing
Requires: torchvision
Requires: plyfile
Requires: computesfm
Requires: compute_sfm
Requires: key_exact
Requires: PyQt5
Requires: vis_gui
Requires: videotoply
Requires: time
Requires: glob
Requires: open3d
Requires: open3d
